setup.py
ST7735/ST7735.py
ST7735/__init__.py
ST7735/fonts/__init__.py
ST7735/fonts/font4x5.py
ST7735/fonts/font5x7.py
ST7735/fonts/font7x10.py
raspi_python_st7735.egg-info/PKG-INFO
raspi_python_st7735.egg-info/SOURCES.txt
raspi_python_st7735.egg-info/dependency_links.txt
raspi_python_st7735.egg-info/requires.txt
raspi_python_st7735.egg-info/top_level.txt